pted/__init__.py
pted/_version.py
pted/pted.py
pted/tests.py
pted/utils.py
pted-1.3.2.dist-info/METADATA
pted-1.3.2.dist-info/WHEEL
pted-1.3.2.dist-info/licenses/LICENSE
pted-1.3.2.dist-info/RECORD
