Metadata-Version: 2.4
Name: pted
Version: 1.3.2
Summary: Implementation of a Permutation Test using the Energy Distance for two sample tests and posterior coverage tests
Project-URL: Homepage, https://github.com/ConnorStoneAstro/pted
Project-URL: Documentation, https://github.com/ConnorStoneAstro/pted
Project-URL: Repository, https://github.com/ConnorStoneAstro/pted
Project-URL: Issues, https://github.com/ConnorStoneAstro/pted/issues
Author-email: Connor Stone <connorstone628@gmail.com>
License: MIT License
License-File: LICENSE
Keywords: Bayesian,machine learning,pytorch,statistics
Classifier: Development Status :: 5 - Production/Stable
Classifier: Intended Audience :: Science/Research
Classifier: License :: OSI Approved :: MIT License
Classifier: Operating System :: OS Independent
Classifier: Programming Language :: Python :: 3
Requires-Python: >=3.9
Requires-Dist: numpy
Requires-Dist: scipy
Requires-Dist: tqdm
Provides-Extra: dev
Requires-Dist: matplotlib; extra == 'dev'
Requires-Dist: pytest-cov<5,>=4.1; extra == 'dev'
Requires-Dist: pytest-mock<4,>=3.12; extra == 'dev'
Requires-Dist: pytest<9,>=8.0; extra == 'dev'
Requires-Dist: torch<3,>=2.0; extra == 'dev'
Provides-Extra: torch
Requires-Dist: torch<3,>=2.0; extra == 'torch'
